dailify/cli.py
dailify/file_handler.py
dailify-0.0.0.5.18.dist-info/METADATA
dailify-0.0.0.5.18.dist-info/RECORD
dailify-0.0.0.5.18.dist-info/WHEEL
dailify-0.0.0.5.18.dist-info/entry_points.txt
dailify-0.0.0.5.18.dist-info/top_level.txt
