Metadata-Version: 2.1
Name: dailify
Version: 0.0.0.5.18
Summary: A Python package helping me whore myself out even further on social media.
Home-page: https://github.com/lucassel/dailify
Author: Lucas Selfslagh
License: MIT
Platform: UNKNOWN
Classifier: License :: OSI Approved :: MIT License
Classifier: Programming Language :: Python :: 3
Classifier: Programming Language :: Python :: 3.7
